{"type":"FeatureCollection","features":[{"type":"Feature","properties":{"name":"Stand Up Against Hate at Alamo Square Park","date":"August 25, 2017"},"geometry":{"type":"Point","coordinates":[-122.43328213691713,37.775887847672436]}},{"type":"Feature","properties":{"name":"Bay Area Rally Against Hate"},"geometry":{"type":"Point","coordinates":[-122.26563870906828,37.871533531287376]}}]}